fondat/hubspot/__init__.py
fondat/hubspot/client.py
fondat/hubspot/contacts/__init__.py
fondat/hubspot/contacts/lists.py
fondat/hubspot/crm/__init__.py
fondat/hubspot/crm/exports.py
fondat/hubspot/crm/model.py
fondat/hubspot/crm/objects.py
fondat/hubspot/crm/owners.py
fondat/hubspot/crm/pipelines.py
fondat/hubspot/crm/properties.py
fondat/hubspot/crm/schemas.py
fondat/hubspot/oauth.py
fondat/hubspot/settings/__init__.py
fondat/hubspot/settings/users.py
fondat_hubspot-4.1.2.dist-info/AUTHORS.md
fondat_hubspot-4.1.2.dist-info/LICENSE
fondat_hubspot-4.1.2.dist-info/METADATA
fondat_hubspot-4.1.2.dist-info/WHEEL
fondat_hubspot-4.1.2.dist-info/RECORD
